pydantic_all_in_one/__init__.py
pydantic_all_in_one/api.py
pydantic_all_in_one/cli/__init__.py
pydantic_all_in_one/cli/async_typer.py
pydantic_all_in_one/config.py
pydantic_all_in_one/examples/__init__.py
pydantic_all_in_one/examples/faststream_in_memory.py
pydantic_all_in_one/graph/__init__.py
pydantic_all_in_one/graph/gqlalchemy_example.py
pydantic_all_in_one/graph/path-to-my-db.db
pydantic_all_in_one/graph/sqlmodel_example.py
pydantic_all_in_one/main.py
pydantic_all_in_one/scheduling/__init__.py
pydantic_all_in_one/scheduling/aioclock_example.py
pydantic_all_in_one/streamer.py
pydantic_all_in_one/utils/__init__.py
pydantic_all_in_one/utils/dir_tools.py
pydantic_all_in_one/vector/__init__.py
pydantic_all_in_one/vector/data/sample-lancedb/my_table.lance/_transactions/0-a5386020-3196-4e6f-a4c1-a1a325773efc.txn
pydantic_all_in_one/vector/data/sample-lancedb/my_table.lance/_transactions/1-799b7081-e69c-4039-a5b9-50cce678eb09.txn
pydantic_all_in_one/vector/data/sample-lancedb/my_table.lance/_versions/1.manifest
pydantic_all_in_one/vector/data/sample-lancedb/my_table.lance/_versions/2.manifest
pydantic_all_in_one/vector/data/sample-lancedb/my_table.lance/data/01c9504c-51fb-4a8b-9ba8-ced0827e6f02.lance
pydantic_all_in_one/vector/lance_example.py
pydantic_all_in_one/vector/path-to-my-db.db
pydantic_all_in_one-2024.10.18.dist-info/METADATA
pydantic_all_in_one-2024.10.18.dist-info/WHEEL
pydantic_all_in_one-2024.10.18.dist-info/entry_points.txt
pydantic_all_in_one-2024.10.18.dist-info/RECORD
