Metadata-Version: 2.1
Name: pydantic-all-in-one
Version: 2024.10.18
Summary: AAll the pydantic projects I want to use together.
Home-page: https://github.com/seanchatmangpt/pydantic-all-in-one
Author: Sean Chatman
Author-email: info@chatmangpt.com
Requires-Python: >=3.12,<4.0
Classifier: Programming Language :: Python :: 3
Classifier: Programming Language :: Python :: 3.12
Classifier: Programming Language :: Python :: 3.13
Requires-Dist: aioclock (>=0.3.0,<0.4.0)
Requires-Dist: asyncer (>=0.0.8,<0.0.9)
Requires-Dist: coloredlogs (>=15.0.1)
Requires-Dist: dslmodel (>=2024.10.18,<2025.0.0)
Requires-Dist: fastapi[all] (>=0.110.1)
Requires-Dist: faststream[cli,redis] (>=0.5.27,<0.6.0)
Requires-Dist: gqlalchemy (>=1.6.0,<2.0.0)
Requires-Dist: gunicorn (>=21.2.0)
Requires-Dist: lancedb (>=0.14.0,<0.15.0)
Requires-Dist: marimo (>=0.9.10,<0.10.0)
Requires-Dist: pandas (>=2.2.3,<3.0.0)
Requires-Dist: pydantic-settings (>=2.6.0,<3.0.0)
Requires-Dist: sqlmodel (>=0.0.22,<0.0.23)
Requires-Dist: typer[all] (>=0.12.0)
Requires-Dist: uvicorn[standard] (>=0.29.0)
Project-URL: Repository, https://github.com/seanchatmangpt/pydantic-all-in-one
